reactivecli/__init__.py
reactivecli/bases/__init__.py
reactivecli/bases/element.py
reactivecli/components/__init__.py
reactivecli/components/menu.py
reactivecli/elements/__init__.py
reactivecli/elements/input.py
reactivecli/elements/link.py
reactivecli/elements/option.py
reactivecli/elements/text.py
reactivecli/elements/title.py
reactivecli/utils/__init__.py
reactivecli/utils/formats.py
reactivecli/utils/text_formatter.py
reactivecli/utils/watchdog.py
reactivecli-1.0.dist-info/LICENSE
reactivecli-1.0.dist-info/METADATA
reactivecli-1.0.dist-info/WHEEL
reactivecli-1.0.dist-info/top_level.txt
reactivecli-1.0.dist-info/RECORD
