Metadata-Version: 2.1
Name: reactivecli
Version: 1.0
Summary: A CLI framework library to build responsive console interfaces
Home-page: https://github.com/brunojunqueira/ReactiveCLI
Author: Bruno Junuqeira
Author-email: brunosdsj@gmail.com
Classifier: Programming Language :: Python :: 3
Classifier: License :: OSI Approved :: MIT License
Classifier: Operating System :: OS Independent
Requires-Python: >=3.7.1
License-File: LICENSE
Requires-Dist: sshkeyboard
